babel_lingua_chameleon/__init__.py
babel_lingua_chameleon/extractors.py
babel_lingua_chameleon/locale/en/LC_MESSAGES/babel-lingua-chameleon.mo
babel_lingua_chameleon/locale/ko/LC_MESSAGES/babel-lingua-chameleon.mo
babel_lingua_chameleon/tests/__init__.py
babel_lingua_chameleon/tests/test_extractors.py
babel_lingua_chameleon/tests/utils.py
babel_lingua_chameleon/tests/fixtures/__init__.py
babel_lingua_chameleon/tests/fixtures/html-page-template.pt
babel_lingua_chameleon/tests/layers/__init__.py
babel_lingua_chameleon-0.1.0.dist-info/METADATA
babel_lingua_chameleon-0.1.0.dist-info/RECORD
babel_lingua_chameleon-0.1.0.dist-info/WHEEL
babel_lingua_chameleon-0.1.0.dist-info/entry_points.txt
babel_lingua_chameleon-0.1.0.dist-info/top_level.txt
