Metadata-Version: 2.1
Name: babel-lingua-chameleon
Version: 0.1.0
Summary: Babel extractor for Chameleon templates
Home-page: https://github.com/mete0r/babel-lingua-chameleon
Author: mete0r
Author-email: arbeitmachtfrei77@gmail.com
License: GNU Affero General Public License v3 or later (AGPLv3+)
Keywords: babel,chameleon,lingua
Platform: UNKNOWN
Classifier: Development Status :: 1 - Planning
Classifier: Intended Audience :: Developers
Classifier: License :: OSI Approved :: GNU Affero General Public License v3 or later (AGPLv3+)
Classifier: Operating System :: OS Independent
Classifier: Programming Language :: Python
Classifier: Programming Language :: Python :: 2.7
Classifier: Programming Language :: Python :: 3.4
Classifier: Programming Language :: Python :: Implementation :: CPython
Provides-Extra: test
Requires-Dist: lingua
Provides-Extra: test
Requires-Dist: zope.testrunner; extra == 'test'
